CEDSSolar/CHS/__init__.py
CEDSSolar/CHS/CHS.py
CEDSSolar/dataIngestion/__init__.py
CEDSSolar/dataIngestion/antioch.py
CEDSSolar/gridSearch/__init__.py
CEDSSolar/gridSearch/DPBayesOpt.py
CEDSSolar/gridSearch/fit.py
CEDSSolar/gridSearch/GridSearch.py
CEDSSolar/gridSearch/GridSearchKevala.py
CEDSSolar/gridSearch/infer.py
CEDSSolar/gridSearch/plot.py
CEDSSolar/gridSearch/query.py
CEDSSolar/gridSearch/results.py
CEDSSolar/location/__init__.py
CEDSSolar/location/statistics.py
CEDSSolar/raksha/__init__.py
CEDSSolar/raksha/SplineFit.py
CEDSSolar/soda/__init__.py
CEDSSolar/soda/soda.py
cedssolar-0.1.1.1.dist-info/METADATA
cedssolar-0.1.1.1.dist-info/WHEEL
cedssolar-0.1.1.1.dist-info/RECORD
