Metadata-Version: 2.1
Name: cedssolar
Version: 0.1.1.1
Summary: A python package to differentially privately infer solar metadata information
License: MIT
Author: Nikhil Ravi
Author-email: nr337@cornell.edu
Requires-Python: >=3.10,<3.12
Classifier: License :: OSI Approved :: MIT License
Classifier: Programming Language :: Python :: 3
Classifier: Programming Language :: Python :: 3.10
Classifier: Programming Language :: Python :: 3.11
Requires-Dist: SQLAlchemy (>=2.0.4,<3.0.0)
Requires-Dist: matplotlib (>=3.7.0,<4.0.0)
Requires-Dist: multiprocess (>=0.70.14,<0.71.0)
Requires-Dist: nbformat (>=4.2.0,<5.0.0)
Requires-Dist: nrel-pysam (>=4.0.0,<5.0.0)
Requires-Dist: numpy (>=1.24.2,<2.0.0)
Requires-Dist: pandas (>=1.5.3,<2.0.0)
Requires-Dist: pandas-dataclasses (>=0.11.0,<0.12.0)
Requires-Dist: plotly (>=5.13.0,<6.0.0)
Requires-Dist: psycopg2-binary (>=2.9.5,<3.0.0)
Requires-Dist: pvlib (>=0.9.4,<0.10.0)
Requires-Dist: pydantic (>=1.10.5,<2.0.0)
Requires-Dist: python-dotenv (>=0.21.1,<0.22.0)
Requires-Dist: pytz (>=2022.7.1,<2023.0.0)
Requires-Dist: scikit-learn (>=1.2.1,<2.0.0)
Requires-Dist: tqdm (>=4.64.1,<5.0.0)
